mpl_interactions/__init__.py
mpl_interactions/_version.py
mpl_interactions/controller.py
mpl_interactions/deprecations.py
mpl_interactions/generic.py
mpl_interactions/helpers.py
mpl_interactions/ipyplot.py
mpl_interactions/mpl_kwargs.py
mpl_interactions/pyplot.py
mpl_interactions/utils.py
mpl_interactions/widgets.py
mpl_interactions/xarray_helpers.py
tests/__init__.py
tests/_util.py
tests/test_controls.py
tests/test_generic.py
tests/test_helpers.py
tests/test_pyplot.py
mpl_interactions-0.24.2.dist-info/LICENSE.txt
mpl_interactions-0.24.2.dist-info/METADATA
mpl_interactions-0.24.2.dist-info/WHEEL
mpl_interactions-0.24.2.dist-info/top_level.txt
mpl_interactions-0.24.2.dist-info/RECORD
