Metadata-Version: 2.1
Name: mpl_interactions
Version: 0.24.2
Summary: Matplotlib aware interact functions
Author: Ian Hunt-Isaak
Author-email: ianhuntisaak@gmail.com
Maintainer-email: ianhuntisaak@gmail.com
License: BSD
Project-URL: Tracker, https://github.com/mpl-extensions/mpl-interactions/issues
Project-URL: Changelog, https://github.com/mpl-extensions/mpl-interactions/releases
Project-URL: Documentation, https://mpl-interactions.rtfd.io
Project-URL: Source, https://github.com/mpl-extensions/mpl-interactions
Keywords: IPython,Jupyter,Matplotlib,Widgets
Platform: Linux
Platform: Mac OS X
Platform: Windows
Classifier: Framework :: Jupyter
Classifier: Framework :: Matplotlib
Classifier: Intended Audience :: Developers
Classifier: Intended Audience :: Science/Research
Classifier: License :: OSI Approved :: BSD License
Classifier: Programming Language :: Python
Classifier: Programming Language :: Python :: 3
Classifier: Programming Language :: Python :: 3.6
Classifier: Programming Language :: Python :: 3.7
Classifier: Programming Language :: Python :: 3.8
Classifier: Programming Language :: Python :: 3.9
Classifier: Programming Language :: Python :: 3.10
Requires-Python: >=3.6
License-File: LICENSE.txt
Requires-Dist: matplotlib>=3.7
Provides-Extra: jupyter
Requires-Dist: ipywidgets>=7.5.0; extra == "jupyter"
Requires-Dist: ipympl>=0.5.8; extra == "jupyter"
Provides-Extra: doc
Requires-Dist: ipywidgets>=7.5.0; extra == "doc"
Requires-Dist: ipympl>=0.5.8; extra == "doc"
Requires-Dist: jupyter-sphinx; extra == "doc"
Requires-Dist: mpl-playback>=0.1.1; extra == "doc"
Requires-Dist: myst-nb; extra == "doc"
Requires-Dist: numpydoc; extra == "doc"
Requires-Dist: Sphinx>=1.5; extra == "doc"
Requires-Dist: sphinx-book-theme; extra == "doc"
Requires-Dist: sphinx-copybutton; extra == "doc"
Requires-Dist: sphinx-gallery>=0.8.2; extra == "doc"
Requires-Dist: sphinx-panels; extra == "doc"
Requires-Dist: sphinx-thebe; extra == "doc"
Requires-Dist: sphinx-togglebutton; extra == "doc"
Requires-Dist: xarray; extra == "doc"
Provides-Extra: sty
Requires-Dist: black; extra == "sty"
Requires-Dist: isort; extra == "sty"
Provides-Extra: test
Requires-Dist: nbval; extra == "test"
Requires-Dist: pandas; extra == "test"
Requires-Dist: PyQt5; extra == "test"
Requires-Dist: pytest; extra == "test"
Requires-Dist: pytest-mpl; extra == "test"
Requires-Dist: requests; extra == "test"
Requires-Dist: scipy; extra == "test"
Requires-Dist: xarray; extra == "test"
Provides-Extra: dev
Requires-Dist: ipywidgets>=7.5.0; extra == "dev"
Requires-Dist: ipympl>=0.5.8; extra == "dev"
Requires-Dist: jupyter-sphinx; extra == "dev"
Requires-Dist: mpl-playback>=0.1.1; extra == "dev"
Requires-Dist: myst-nb; extra == "dev"
Requires-Dist: numpydoc; extra == "dev"
Requires-Dist: Sphinx>=1.5; extra == "dev"
Requires-Dist: sphinx-book-theme; extra == "dev"
Requires-Dist: sphinx-copybutton; extra == "dev"
Requires-Dist: sphinx-gallery>=0.8.2; extra == "dev"
Requires-Dist: sphinx-panels; extra == "dev"
Requires-Dist: sphinx-thebe; extra == "dev"
Requires-Dist: sphinx-togglebutton; extra == "dev"
Requires-Dist: xarray; extra == "dev"
Requires-Dist: ipywidgets>=7.5.0; extra == "dev"
Requires-Dist: ipympl>=0.5.8; extra == "dev"
Requires-Dist: black; extra == "dev"
Requires-Dist: isort; extra == "dev"
Requires-Dist: nbval; extra == "dev"
Requires-Dist: pandas; extra == "dev"
Requires-Dist: PyQt5; extra == "dev"
Requires-Dist: pytest; extra == "dev"
Requires-Dist: pytest-mpl; extra == "dev"
Requires-Dist: requests; extra == "dev"
Requires-Dist: scipy; extra == "dev"
Requires-Dist: xarray; extra == "dev"
Requires-Dist: pre-commit; extra == "dev"
Requires-Dist: sphinx-autobuild; extra == "dev"
Requires-Dist: tox>=1.9; extra == "dev"
